setup.py
bi_powerhouse/__init__.py
bi_powerhouse.egg-info/PKG-INFO
bi_powerhouse.egg-info/SOURCES.txt
bi_powerhouse.egg-info/dependency_links.txt
bi_powerhouse.egg-info/not-zip-safe
bi_powerhouse.egg-info/requires.txt
bi_powerhouse.egg-info/top_level.txt
bi_powerhouse/utilities/__init__.py
bi_powerhouse/utilities/get_secret.py
bi_powerhouse/utilities/run_query.py
bi_powerhouse/utilities/s3_upload.py
bi_powerhouse/utilities/sqs_receive.py
bi_powerhouse/utilities/sqs_send.py
bi_powerhouse/utilities/write_to_csv.py
bi_powerhouse/utilities/db_connections/__init__.py
bi_powerhouse/utilities/db_connections/cursor_creator.py
bi_powerhouse/utilities/db_connections/individual_query_runner.py