Metadata-Version: 1.0
Name: bi-powerhouse
Version: 0.5
Summary: Functions to simplify day to day BI work.
Home-page: https://github.com/ksco92/bi_powerhouse
Author: Rodrigo Carvajal
Author-email: rodrigocf_92@hotmail.com
License: MIT
Platform: UNKNOWN
